rundpo/__init__.py
rundpo/client.py
rundpo/example.py
rundpo/types.py
rundpo/utils.py
rundpo-0.2.1.dist-info/LICENSE
rundpo-0.2.1.dist-info/METADATA
rundpo-0.2.1.dist-info/WHEEL
rundpo-0.2.1.dist-info/top_level.txt
rundpo-0.2.1.dist-info/RECORD
