Metadata-Version: 2.2
Name: rundpo
Version: 0.2.1
Summary: A modern, async-first Python client for the Rundpo API
Author-email: Rundpo Team <team@rundpo.com>
Project-URL: Homepage, https://github.com/rundpo/rundpo-python
Project-URL: Bug Tracker, https://github.com/rundpo/rundpo-python/issues
Classifier: Programming Language :: Python :: 3
Classifier: License :: OSI Approved :: MIT License
Classifier: Operating System :: OS Independent
Classifier: Development Status :: 4 - Beta
Classifier: Intended Audience :: Developers
Classifier: Topic :: Scientific/Engineering :: Artificial Intelligence
Requires-Python: >=3.8
License-File: LICENSE
Requires-Dist: aiohttp>=3.8.0
Requires-Dist: requests>=2.28.0
Requires-Dist: tqdm>=4.65.0
